shirly_client/__init__.py
shirly_client/client.py
shirly_client/models.py
shirly_client-0.1.1.dist-info/licenses/LICENSE.txt
shirly_client-0.1.1.dist-info/METADATA
shirly_client-0.1.1.dist-info/WHEEL
shirly_client-0.1.1.dist-info/top_level.txt
shirly_client-0.1.1.dist-info/RECORD
