Metadata-Version: 2.4
Name: shirly-client
Version: 0.1.1
Summary: Python client for the Shirly scheduler API
Author: Shirly
License-Expression: LicenseRef-ShirlyProprietary
Project-URL: Homepage, https://example.com/shirly
Requires-Python: >=3.10
License-File: LICENSE.txt
Requires-Dist: httpx>=0.25
Provides-Extra: dev
Requires-Dist: pytest>=7.4; extra == "dev"
Dynamic: license-file
